mikasa/__init__.py
mikasa/__main__.py
mikasa/config.py
mikasa/db.py
mikasa/main.py
mikasa-1.1.8.dist-info/entry_points.txt
mikasa-1.1.8.dist-info/WHEEL
mikasa-1.1.8.dist-info/METADATA
mikasa-1.1.8.dist-info/RECORD
