Metadata-Version: 2.1
Name: mikasa
Version: 1.1.8
Summary: Simple Project Manager 
Author: Hussein Naim
Author-email: phusseinnaim@gmail.com
Requires-Python: >=3.9,<4.0
Classifier: Programming Language :: Python :: 3
Classifier: Programming Language :: Python :: 3.10
Classifier: Programming Language :: Python :: 3.9
Requires-Dist: typer[all] (>=0.4.2,<0.5.0)
